pyconf/__init__.py
pyconf/pyconf.py
pyconf_primecoder-0.1.0.dist-info/LICENSE
pyconf_primecoder-0.1.0.dist-info/METADATA
pyconf_primecoder-0.1.0.dist-info/WHEEL
pyconf_primecoder-0.1.0.dist-info/top_level.txt
pyconf_primecoder-0.1.0.dist-info/RECORD
