Metadata-Version: 2.1
Name: pyconf-primecoder
Version: 0.1.0
Summary: Python Configurator - setup python configuration and environment
Home-page: https://github.com/primecoder/shell-config
Author: Ace Authors
Author-email: primecoder.authors@gmail.com
License: UNKNOWN
Platform: UNKNOWN
Classifier: Programming Language :: Python :: 3
Classifier: License :: OSI Approved :: MIT License
Classifier: Operating System :: OS Independent
Requires-Python: >=3.6
